muhamadyorg_nik/__init__.py
muhamadyorg_nik/main.py
muhamadyorg_nik-0.1.2.dist-info/METADATA
muhamadyorg_nik-0.1.2.dist-info/WHEEL
muhamadyorg_nik-0.1.2.dist-info/entry_points.txt
muhamadyorg_nik-0.1.2.dist-info/top_level.txt
muhamadyorg_nik-0.1.2.dist-info/RECORD
