Metadata-Version: 2.4
Name: muhamadyorg-nik
Version: 0.1.2
Summary: CLI tool to print text in figlet ASCII art style
Author: Muhamadyor
License: MIT
Classifier: Programming Language :: Python :: 3
Classifier: License :: OSI Approved :: MIT License
Classifier: Operating System :: OS Independent
Requires-Python: >=3.6
Requires-Dist: pyfiglet
Dynamic: author
Dynamic: classifier
Dynamic: license
Dynamic: requires-dist
Dynamic: requires-python
Dynamic: summary
